charm_gems-1.3.3.dist-info/LICENSE
charm_gems-1.3.3.dist-info/top_level.txt
charm_gems-1.3.3.dist-info/WHEEL
charm_gems-1.3.3.dist-info/RECORD
charm_gems-1.3.3.dist-info/METADATA
charm_gems/__init__.py
charm_gems/gemsbindings.cpython-310-x86_64-linux-gnu.so
