Metadata-Version: 2.1
Name: charm-gems
Version: 1.3.3
Summary: Python bindings of the gems segmentation package.
Home-page: https://github.com/simnibs/charm-gems
Author: Koen Van Leemput, Oula Puonti and Juan Eugenio Iglesias
Author-email: oulap@drcmr.dk
License: GPL3
License-File: LICENSE
Requires-Dist: numpy
